segmentationextractors/__init__.py
segmentationextractors/segmentationextractor.py
segmentationextractors/version.py
segmentationextractors/numpyextractor/__init__.py
segmentationextractors/numpyextractor/numpysegmentationextractor.py
segmentationextractors/nwbextractor/__init__.py
segmentationextractors/nwbextractor/nwbsegmentationextractor.py
segmentationextractors/schnitzerextractor/__init__.py
segmentationextractors/schnitzerextractor/cnmfesegmentationextractor.py
segmentationextractors/schnitzerextractor/extractsegmentationextractor.py
segmentationextractors/simaextractor/__init__.py
segmentationextractors/simaextractor/simasegmentationextractor.py
segmentationextractors-0.1.0.dist-info/LICENSE.txt
segmentationextractors-0.1.0.dist-info/METADATA
segmentationextractors-0.1.0.dist-info/WHEEL
segmentationextractors-0.1.0.dist-info/top_level.txt
segmentationextractors-0.1.0.dist-info/RECORD
