Metadata-Version: 2.1
Name: segmentationextractors
Version: 0.1.0
Summary: Python module for extracting optical physiology ROIs and traces for various file types and formats
Home-page: https://github.com/ben-dichter-consulting/segmentationextractors
Author: Saksham Sharda, Ben Dichter
Author-email: saksham20.sharda@gmail.com
License: UNKNOWN
Platform: UNKNOWN
Classifier: Programming Language :: Python :: 3
Classifier: License :: OSI Approved :: Apache Software License
Classifier: Operating System :: OS Independent
Classifier: Intended Audience :: Science/Research
Requires-Dist: pynwb
Requires-Dist: sima
Requires-Dist: dill
Requires-Dist: lazy-ops
